KalturaClient/Base.py
KalturaClient/Client.py
KalturaClient/Client.pyi
KalturaClient/__init__.py
KalturaClient/exceptions.py
KalturaClient/Plugins/ActivitiBusinessProcessNotification.py
KalturaClient/Plugins/ActivitiBusinessProcessNotification.pyi
KalturaClient/Plugins/AdCuePoint.py
KalturaClient/Plugins/AdCuePoint.pyi
KalturaClient/Plugins/Annotation.py
KalturaClient/Plugins/Annotation.pyi
KalturaClient/Plugins/ApFeedDropFolder.py
KalturaClient/Plugins/ApFeedDropFolder.pyi
KalturaClient/Plugins/Aspera.py
KalturaClient/Plugins/Aspera.pyi
KalturaClient/Plugins/AttUverseDistribution.py
KalturaClient/Plugins/AttUverseDistribution.pyi
KalturaClient/Plugins/Attachment.py
KalturaClient/Plugins/Attachment.pyi
KalturaClient/Plugins/Audit.py
KalturaClient/Plugins/Audit.pyi
KalturaClient/Plugins/AvnDistribution.py
KalturaClient/Plugins/AvnDistribution.pyi
KalturaClient/Plugins/Beacon.py
KalturaClient/Plugins/Beacon.pyi
KalturaClient/Plugins/BooleanNotification.py
KalturaClient/Plugins/BooleanNotification.pyi
KalturaClient/Plugins/BpmEventNotificationIntegration.py
KalturaClient/Plugins/BpmEventNotificationIntegration.pyi
KalturaClient/Plugins/BulkUpload.py
KalturaClient/Plugins/BulkUpload.pyi
KalturaClient/Plugins/BulkUploadCsv.py
KalturaClient/Plugins/BulkUploadCsv.pyi
KalturaClient/Plugins/BulkUploadFilter.py
KalturaClient/Plugins/BulkUploadFilter.pyi
KalturaClient/Plugins/BulkUploadXml.py
KalturaClient/Plugins/BulkUploadXml.pyi
KalturaClient/Plugins/Bumper.py
KalturaClient/Plugins/Bumper.pyi
KalturaClient/Plugins/BusinessProcessNotification.py
KalturaClient/Plugins/BusinessProcessNotification.pyi
KalturaClient/Plugins/Caption.py
KalturaClient/Plugins/Caption.pyi
KalturaClient/Plugins/CaptionSearch.py
KalturaClient/Plugins/CaptionSearch.pyi
KalturaClient/Plugins/CaptureSpace.py
KalturaClient/Plugins/CaptureSpace.pyi
KalturaClient/Plugins/Cielo24.py
KalturaClient/Plugins/Cielo24.pyi
KalturaClient/Plugins/CodeCuePoint.py
KalturaClient/Plugins/CodeCuePoint.pyi
kalturaapiclient-22.12.0.dist-info/licenses/LICENSE.txt
kalturaapiclient-22.12.0.dist-info/METADATA
kalturaapiclient-22.12.0.dist-info/WHEEL
kalturaapiclient-22.12.0.dist-info/top_level.txt
kalturaapiclient-22.12.0.dist-info/RECORD
