Metadata-Version: 2.4
Name: KalturaApiClient
Version: 22.12.0
Summary: A Python module for accessing the Kaltura API.
Home-page: https://github.com/kaltura/KalturaGeneratedAPIClientsPython
License: AGPLv3+
Keywords: Kaltura API client
Classifier: Development Status :: 5 - Production/Stable
Classifier: Intended Audience :: Developers
Classifier: Topic :: Software Development :: Build Tools
Classifier: License :: OSI Approved :: GNU Affero General Public License v3 or later (AGPLv3+)
Classifier: Programming Language :: Python :: 2.7
Classifier: Programming Language :: Python :: 3
Classifier: Programming Language :: Python :: 3.3
Classifier: Programming Language :: Python :: 3.4
Classifier: Programming Language :: Python :: 3.5
License-File: LICENSE.txt
Requires-Dist: requests>=2.4.2
Requires-Dist: requests-toolbelt
Requires-Dist: six
Dynamic: classifier
Dynamic: description
Dynamic: description-content-type
Dynamic: home-page
Dynamic: keywords
Dynamic: license
Dynamic: license-file
Dynamic: requires-dist
Dynamic: summary
